region_search/__init__.py
region_search/_version.py
region_search/cli.py
region_search/lookup.py
region_search/ip/__init__.py
region_search/ip/lookup.py
region_search/phone/__init__.py
region_search/phone/lookup.py
region_search-0.0.1.dist-info/LICENSE
region_search-0.0.1.dist-info/METADATA
region_search-0.0.1.dist-info/WHEEL
region_search-0.0.1.dist-info/entry_points.txt
region_search-0.0.1.dist-info/top_level.txt
region_search-0.0.1.dist-info/RECORD
