Metadata-Version: 2.1
Name: region-search
Version: 0.0.1
Summary: 归属地查询
Home-page: https://github.com/sleepingF0x/RegionSearch
Author: sleepingF0x
Author-email: agent.999th@gmail.com
License: MIT
Keywords: region search
Platform: UNKNOWN
Classifier: Development Status :: 3 - Alpha
Classifier: Intended Audience :: Developers
Classifier: License :: OSI Approved :: MIT License
Classifier: Operating System :: OS Independent
Classifier: Programming Language :: Python :: 3
Classifier: Programming Language :: Python :: 3.5
Classifier: Programming Language :: Python :: 3.6
Classifier: Programming Language :: Python :: 3.7
Classifier: Programming Language :: Python :: 3.8
Classifier: Programming Language :: Python :: 3.9
Requires-Python: >=3.5
